odoo/addons/purchase_order_archive_draft/README.rst
odoo/addons/purchase_order_archive_draft/__init__.py
odoo/addons/purchase_order_archive_draft/__manifest__.py
odoo/addons/purchase_order_archive_draft/i18n/es.po
odoo/addons/purchase_order_archive_draft/models/__init__.py
odoo/addons/purchase_order_archive_draft/models/purchase_order.py
odoo/addons/purchase_order_archive_draft/readme/CONTRIBUTORS.md
odoo/addons/purchase_order_archive_draft/readme/DESCRIPTION.md
odoo/addons/purchase_order_archive_draft/readme/USAGE.md
odoo/addons/purchase_order_archive_draft/static/description/icon.png
odoo/addons/purchase_order_archive_draft/static/description/index.html
odoo_addon_purchase_order_archive_draft-16.0.1.0.0.1.dist-info/METADATA
odoo_addon_purchase_order_archive_draft-16.0.1.0.0.1.dist-info/WHEEL
odoo_addon_purchase_order_archive_draft-16.0.1.0.0.1.dist-info/top_level.txt
odoo_addon_purchase_order_archive_draft-16.0.1.0.0.1.dist-info/RECORD
